{
  "title": "Logo-02",
  "metadata": {
    "image": null,
    "title": "Logo-02",
    "alt": {
      "en": "Logo-02",
      "el": ""
    },
    "caption": {
      "en": "",
      "el": ""
    },
    "description": {
      "en": "",
      "el": ""
    },
    "credit": "",
    "copyright": "",
    "decorative": false,
    "preferredUsage": "Existing website image",
    "width": null,
    "height": null,
    "fileType": "png",
    "externalSourceUrl": "/wp-clone/wp-content/uploads/2025/03/Logo-02.png",
    "tags": []
  }
}
