{
  "question": "Πόσος χρόνος χρειάζεται για να δω αποτελέσματα SEO;",
  "greekQuestion": "Πόσος χρόνος χρειάζεται για να δω αποτελέσματα SEO;",
  "answer": {
    "en": "",
    "el": "Τα περισσότερα sites βλέπουν ουσιαστική κίνηση μέσα σε δύο έως τρεις μήνες, με πιο δυνατά αποτελέσματα να χτίζονται σταδιακά. Οι αυτοματισμοί και τα dashboards μπορούν να εξοικονομήσουν χρόνο πιο άμεσα."
  },
  "category": "General",
  "relatedService": null,
  "relatedPage": null,
  "tags": [],
  "displayOrder": 7,
  "active": true
}
